LinguAI/__init__.py
LinguAI-0.1.0.dist-info/LICENSE
LinguAI-0.1.0.dist-info/METADATA
LinguAI-0.1.0.dist-info/WHEEL
LinguAI-0.1.0.dist-info/top_level.txt
LinguAI-0.1.0.dist-info/RECORD
